question_builder/__init__.py
question_builder/bp/__init__.py
question_builder/bp/config.py
question_builder/bp/dictionary_factory.py
question_builder/bp/exceptions/__init__.py
question_builder/bp/exceptions/dictionary_exceptions.py
question_builder/bp/exceptions/dual_video_exceptions.py
question_builder/bp/exceptions/lexemas_exceptions.py
question_builder/bp/exceptions/missing_params_exceptions.py
question_builder/bp/exceptions/pos_exceptions.py
question_builder/bp/exceptions/question_creator_exception.py
question_builder/bp/exceptions/tag_exceptions.py
question_builder/bp/question_builder.py
question_builder/bp/question_creators/__init__.py
question_builder/bp/question_creators/dual_video_question_creator.py
question_builder/bp/question_creators/general/__init__.py
question_builder/bp/question_creators/general/antonym_question_creator.py
question_builder/bp/question_creators/general/choice_english_definitions_question_creator.py
question_builder/bp/question_creators/general/choice_spanish_definitions_question_creator.py
question_builder/bp/question_creators/general/conjugation_question_creator.py
question_builder/bp/question_creators/general/dual_video_spanish_definitions_question_creator.py
question_builder/bp/question_creators/general/fullword_scrabble_question_creator.py
question_builder/bp/question_creators/general/fullword_typing_question_creator.py
question_builder/bp/question_creators/general/gap_question_creator.py
question_builder/bp/question_creators/general/intruder_question_creator.py
question_builder/bp/question_creators/general/means_like_question_creator.py
question_builder/bp/question_creators/general/minimal_pairs_question_creator.py
question_builder/bp/question_creators/general/multisynonym_question_creator.py
question_builder/bp/question_creators/general/partword_typing_question_creator.py
question_builder/bp/question_creators/general/relnoun_question_creator.py
question_builder/bp/question_creators/general/sentence_scrabble_question_creator.py
backend_library_createquestions-0.1.0.dist-info/LICENSE
backend_library_createquestions-0.1.0.dist-info/WHEEL
backend_library_createquestions-0.1.0.dist-info/METADATA
backend_library_createquestions-0.1.0.dist-info/RECORD
